lmprep-0.4.1.data/purelib/lmprep/__init__.py
lmprep-0.4.1.data/purelib/lmprep/cli.py
lmprep-0.4.1.data/purelib/lmprep/default_config.yml
lmprep-0.4.1.data/purelib/lmprep/binaries/darwin_universal2/lm
lmprep-0.4.1.data/purelib/lmprep/binaries/linux_x86_64/lm
lmprep-0.4.1.data/purelib/lmprep/binaries/win_amd64/lm.exe
lmprep-0.4.1.dist-info/LICENSE
lmprep-0.4.1.dist-info/METADATA
lmprep-0.4.1.dist-info/WHEEL
lmprep-0.4.1.dist-info/entry_points.txt
lmprep-0.4.1.dist-info/top_level.txt
lmprep-0.4.1.dist-info/RECORD
