Metadata-Version: 2.1
Name: lmprep
Version: 0.4.1
Summary: A tool for preparing your codebase for use with LLMs
Author: bcherb2
License: MIT
Project-URL: Homepage, https://github.com/bcherb2/lmprep
Project-URL: Repository, https://github.com/bcherb2/lmprep.git
Keywords: llm,code,preparation
Classifier: Development Status :: 3 - Alpha
Classifier: Intended Audience :: Developers
Classifier: License :: OSI Approved :: MIT License
Classifier: Operating System :: POSIX :: Linux
Classifier: Operating System :: Microsoft :: Windows
Classifier: Operating System :: MacOS
Classifier: Programming Language :: Python :: 3
Classifier: Programming Language :: Python :: 3.8
Classifier: Programming Language :: Python :: 3.9
Classifier: Programming Language :: Python :: 3.10
Classifier: Programming Language :: Python :: 3.11
Classifier: Programming Language :: Python :: 3.12
Requires-Python: >=3.8
License-File: LICENSE
